profiles_mlcorelib/__init__.py
profiles_mlcorelib/predict.py
profiles_mlcorelib/train.py
profiles_mlcorelib/config/model_configs.yaml
profiles_mlcorelib/connectors/BigQueryConnector.py
profiles_mlcorelib/connectors/CommonWarehouseConnector.py
profiles_mlcorelib/connectors/Connector.py
profiles_mlcorelib/connectors/ConnectorFactory.py
profiles_mlcorelib/connectors/RedshiftConnector.py
profiles_mlcorelib/connectors/SnowflakeConnector.py
profiles_mlcorelib/connectors/__init__.py
profiles_mlcorelib/connectors/wh/__init__.py
profiles_mlcorelib/connectors/wh/bigquery_base_connector.py
profiles_mlcorelib/connectors/wh/connector_base.py
profiles_mlcorelib/connectors/wh/profiles_connector.py
profiles_mlcorelib/connectors/wh/redshift_base_connector.py
profiles_mlcorelib/ml_core/__init__.py
profiles_mlcorelib/ml_core/preprocess_and_predict.py
profiles_mlcorelib/ml_core/preprocess_and_train.py
profiles_mlcorelib/processors/K8sProcessor.py
profiles_mlcorelib/processors/LocalProcessor.py
profiles_mlcorelib/processors/Processor.py
profiles_mlcorelib/processors/ProcessorFactory.py
profiles_mlcorelib/processors/SnowflakeProcessor.py
profiles_mlcorelib/processors/__init__.py
profiles_mlcorelib/py_native/__init__.py
profiles_mlcorelib/py_native/attribution_report.py
profiles_mlcorelib/py_native/llm.py
profiles_mlcorelib/py_native/prediction.py
profiles_mlcorelib/py_native/propensity.py
profiles_mlcorelib/py_native/training.py
profiles_mlcorelib/py_native/warehouse.py
profiles_mlcorelib/py_native/id_stitcher/__init__.py
profiles_mlcorelib/py_native/id_stitcher/audit.py
profiles_mlcorelib/py_native/id_stitcher/cluster_report.py
profiles_mlcorelib/py_native/id_stitcher/config.py
profiles_mlcorelib/py_native/id_stitcher/consent_manager.py
profiles_mlcorelib/py_native/id_stitcher/llm_report.py
profiles_mlcorelib/py_native/id_stitcher/prompts.py
profiles_mlcorelib/py_native/id_stitcher/table_report.py
profiles_mlcorelib/py_native/id_stitcher/yaml_report.py
profiles_mlcorelib-0.8.11.dist-info/METADATA
profiles_mlcorelib-0.8.11.dist-info/WHEEL
profiles_mlcorelib-0.8.11.dist-info/top_level.txt
profiles_mlcorelib-0.8.11.dist-info/RECORD
