Metadata-Version: 2.4
Name: profiles_mlcorelib
Version: 0.8.11
Author: rudderstack
Classifier: Programming Language :: Python :: 3
Classifier: Intended Audience :: Developers
Classifier: License :: OSI Approved :: MIT License
Requires-Dist: profiles_rudderstack>=0.20.0
Requires-Dist: cachetools>=5.3.2
Requires-Dist: hyperopt>=0.2.7
Requires-Dist: joblib>=1.3.2
Requires-Dist: matplotlib>=3.7.5
Requires-Dist: seaborn>=0.13.1
Requires-Dist: numpy>=1.24.4
Requires-Dist: pandas<2.2.0,>=2.0.3
Requires-Dist: pyarrow>=14.0.2
Requires-Dist: PyYAML>=6.0.1
Requires-Dist: scikit_learn<=1.4.2,>=1.4.0
Requires-Dist: shap<0.47.0,>=0.44.0
Requires-Dist: xgboost>=2.0.3
Requires-Dist: redshift-connector>=2.0.918
Requires-Dist: pandas-redshift>=2.0.5
Requires-Dist: sqlalchemy-redshift>=0.8.14
Requires-Dist: sqlalchemy<2.0.0,>=1.4.51
Requires-Dist: snowflake_connector_python>=3.6.0
Requires-Dist: google-cloud-bigquery<3.28.0,>=3.17.2
Requires-Dist: sqlalchemy-bigquery>=1.9.0
Requires-Dist: db-dtypes>=1.2.0
Requires-Dist: pycaret==3.3.1
Requires-Dist: boto3>=1.34.153
Requires-Dist: google-auth-oauthlib>=1.0.0
Requires-Dist: cryptography>=42.0.2
Requires-Dist: plotly>=5.24.1
Requires-Dist: snowflake-snowpark-python[pandas]<1.26.0,>=1.11.1
Requires-Dist: networkx
Requires-Dist: pyvis
Requires-Dist: rudder-sdk-python
Requires-Dist: ruamel.yaml<0.19.0,>=0.18.6
Requires-Dist: colorama>=0.4.6
Requires-Dist: pytest
Dynamic: author
Dynamic: classifier
Dynamic: description-content-type
Dynamic: requires-dist
